csv_parser/__init__.py
csv_parser/processor.py
csv_parser_cnic_test_2025-0.3.3.dist-info/METADATA
csv_parser_cnic_test_2025-0.3.3.dist-info/WHEEL
csv_parser_cnic_test_2025-0.3.3.dist-info/top_level.txt
csv_parser_cnic_test_2025-0.3.3.dist-info/RECORD
